LICENSE
MANIFEST.in
README.md
setup.py
rakuten/__init__.py
rakuten/client.py
rakuten.egg-info/PKG-INFO
rakuten.egg-info/SOURCES.txt
rakuten.egg-info/dependency_links.txt
rakuten.egg-info/requires.txt
rakuten.egg-info/top_level.txt
rakuten/apis/__init__.py
rakuten/apis/api_exception.py
rakuten/apis/base_api.py
rakuten/apis/travel_api.py