Metadata-Version: 1.1
Name: rakuten
Version: 0.1.4
Summary: Rakuten API client.
Home-page: https://github.com/claudetech/python_rakuten
Author: Daniel Perez
Author-email: daniel@claudetech.com
License: LICENSE
Platform: UNKNOWN
Classifier: Development Status :: 2 - Pre-Alpha
Classifier: Intended Audience :: Developers
Classifier: License :: OSI Approved :: MIT License
Classifier: Operating System :: OS Independent
Classifier: Programming Language :: Python :: 3
Classifier: Topic :: Software Development :: Libraries
